rsr/Classdef.py
rsr/__init__.py
rsr/detect.py
rsr/fit.py
rsr/invert.py
rsr/pdf.py
rsr/run.py
rsr/sample.py
rsr/utils.py
rsr-1.0.8.dist-info/licenses/LICENSE.md
rsr-1.0.8.dist-info/METADATA
rsr-1.0.8.dist-info/WHEEL
rsr-1.0.8.dist-info/top_level.txt
rsr-1.0.8.dist-info/RECORD
